main.py
zoomcutter-0.2.3.dist-info/licenses/LICENSE
zoomcutter-0.2.3.dist-info/METADATA
zoomcutter-0.2.3.dist-info/WHEEL
zoomcutter-0.2.3.dist-info/entry_points.txt
zoomcutter-0.2.3.dist-info/top_level.txt
zoomcutter-0.2.3.dist-info/RECORD
