Metadata-Version: 2.4
Name: zoomcutter
Version: 0.2.3
Summary: Automatically process Zoom recordings to switch between speaker-only and side-by-side views based on screen sharing chapters
Author-email: Welton Rodrigo <rodrigo@familianascimento.org>
License: MIT
Project-URL: Homepage, https://github.com/weltonrodrigo/zoomcutter
Project-URL: Repository, https://github.com/weltonrodrigo/zoomcutter
Project-URL: Issues, https://github.com/weltonrodrigo/zoomcutter/issues
Keywords: zoom,video,processing,ffmpeg,screen-sharing,presentation
Classifier: Development Status :: 4 - Beta
Classifier: Intended Audience :: Developers
Classifier: Intended Audience :: Education
Classifier: License :: OSI Approved :: MIT License
Classifier: Programming Language :: Python :: 3
Classifier: Programming Language :: Python :: 3.11
Classifier: Programming Language :: Python :: 3.12
Classifier: Topic :: Multimedia :: Video
Classifier: Topic :: Multimedia :: Video :: Conversion
Requires-Python: >=3.11
License-File: LICENSE
Requires-Dist: click>=8.3.0
Dynamic: license-file
